setup.cfg
setup.py
metaparticle_pkg/__init__.py
metaparticle_pkg/containerize.py
metaparticle_pkg/option.py
metaparticle_pkg.egg-info/PKG-INFO
metaparticle_pkg.egg-info/SOURCES.txt
metaparticle_pkg.egg-info/dependency_links.txt
metaparticle_pkg.egg-info/not-zip-safe
metaparticle_pkg.egg-info/requires.txt
metaparticle_pkg.egg-info/top_level.txt
metaparticle_pkg/builder/__init__.py
metaparticle_pkg/builder/docker_builder.py
metaparticle_pkg/builder/test/__init__.py
metaparticle_pkg/builder/test/test_docker_builder.py
metaparticle_pkg/runner/__init__.py
metaparticle_pkg/runner/docker_runner.py
metaparticle_pkg/runner/metaparticle.py
metaparticle_pkg/runner/test/__init__.py
metaparticle_pkg/runner/test/test_docker_runner.py
metaparticle_pkg/runner/test/test_metaparticle.py
metaparticle_pkg/test/__init__.py
metaparticle_pkg/test/test_containerize.py
metaparticle_pkg/test/test_option.py